<?xml version="1.0" encoding="UTF-8"?>
<JobHistory>
	<History>
		<JobID>[[JobID]]</JobID>
		<JobHistoryMessage>[[JobHistoryMessage]]</JobHistoryMessage>
		<Filter>[[Filter]]</Filter>
		<Category>[[Category]]</Category>
		<Description>[[Description]]</Description>		
		<IsImportant>[[IsImportant]]</IsImportant>
		<CreatedBy>[[CreatedBy]]</CreatedBy>
		<CreatedDate>[[CreatedDate]]</CreatedDate>
		<HistoryType>[[HistoryType]]</HistoryType>
		<NoteID>[[NoteID]]</NoteID>
		<IsDeleted>[[IsDeleted]]</IsDeleted>
	</History>
</JobHistory>
